odoo8_addon_l10n_br_account_product-8.0.3.0.0-py2.7-nspkg.pth
odoo8_addon_l10n_br_account_product-8.0.3.0.0.dist-info/top_level.txt
odoo8_addon_l10n_br_account_product-8.0.3.0.0.dist-info/WHEEL
odoo8_addon_l10n_br_account_product-8.0.3.0.0.dist-info/RECORD
odoo8_addon_l10n_br_account_product-8.0.3.0.0.dist-info/metadata.json
odoo8_addon_l10n_br_account_product-8.0.3.0.0.dist-info/DESCRIPTION.rst
odoo8_addon_l10n_br_account_product-8.0.3.0.0.dist-info/METADATA
odoo8_addon_l10n_br_account_product-8.0.3.0.0.dist-info/namespace_packages.txt
odoo_addons/l10n_br_account_product/__openerp__.py
odoo_addons/l10n_br_account_product/__init__.py
odoo_addons/l10n_br_account_product/README.rst
odoo_addons/l10n_br_account_product/account_invoice_workflow.xml
odoo_addons/l10n_br_account_product/l10n_br_account_product_sequence.xml
odoo_addons/l10n_br_account_product/security/l10n_br_account_product_security.xml
odoo_addons/l10n_br_account_product/security/ir.model.access.csv
odoo_addons/l10n_br_account_product/report/account_invoice_report_view.xml
odoo_addons/l10n_br_account_product/report/account_invoice_report.py
odoo_addons/l10n_br_account_product/report/__init__.py
odoo_addons/l10n_br_account_product/migrations/8.0.2.0.0/pre-migration.py
odoo_addons/l10n_br_account_product/models/product.py
odoo_addons/l10n_br_account_product/models/res_partner.py
odoo_addons/l10n_br_account_product/models/account_invoice.py
odoo_addons/l10n_br_account_product/models/l10n_br_account.py
odoo_addons/l10n_br_account_product/models/account.py
odoo_addons/l10n_br_account_product/models/__init__.py
odoo_addons/l10n_br_account_product/models/res_company.py
odoo_addons/l10n_br_account_product/models/res_country.py
odoo_addons/l10n_br_account_product/models/account_product_fiscal_classification.py
odoo_addons/l10n_br_account_product/models/l10n_br_account_product.py
odoo_addons/l10n_br_account_product/i18n/pt_BR.po
odoo_addons/l10n_br_account_product/wizard/l10n_br_account_nfe_export_invoice.py
odoo_addons/l10n_br_account_product/wizard/l10n_br_account_nfe_export_invoice_view.xml
odoo_addons/l10n_br_account_product/wizard/l10n_br_account_document_status_sefaz_view.xml
odoo_addons/l10n_br_account_product/wizard/l10n_br_account_document_status_sefaz.py
odoo_addons/l10n_br_account_product/wizard/l10n_br_account_invoice_costs_ratio_view.xml
odoo_addons/l10n_br_account_product/wizard/account_invoice_refund.py
